free_bandcamp_downloader/__init__.py
free_bandcamp_downloader/__main__.py
free_bandcamp_downloader/bandcamp_http_adapter.py
free_bandcamp_downloader/bc_free_downloader.py
free_bandcamp_downloader-0.5.1.dist-info/METADATA
free_bandcamp_downloader-0.5.1.dist-info/WHEEL
free_bandcamp_downloader-0.5.1.dist-info/entry_points.txt
free_bandcamp_downloader-0.5.1.dist-info/RECORD
