Metadata-Version: 2.4
Name: free-bandcamp-downloader
Version: 0.5.1
Summary: Download free and name-your-price albums from Bandcamp in lossless quality
License: MIT
Author: 7x11x13
Author-email: x7x11x13@gmail.com
Requires-Python: >=3.8,<4.0
Classifier: License :: OSI Approved :: MIT License
Classifier: Programming Language :: Python :: 3
Classifier: Programming Language :: Python :: 3.8
Classifier: Programming Language :: Python :: 3.9
Classifier: Programming Language :: Python :: 3.10
Classifier: Programming Language :: Python :: 3.11
Classifier: Programming Language :: Python :: 3.12
Classifier: Programming Language :: Python :: 3.13
Classifier: Programming Language :: Python :: 3.14
Requires-Dist: beautifulsoup4 (>=4.12.2,<5.0.0)
Requires-Dist: docopt-ng (>=0.9.0,<0.10.0)
Requires-Dist: mutagen (>=1.47.0,<2.0.0)
Requires-Dist: pyrfc6266 (>=1.0.2,<2.0.0)
Requires-Dist: python-guerrillamail (>=0.2.0,<0.3.0)
Requires-Dist: requests (>=2.31.0,<3.0.0)
Requires-Dist: tqdm (>=4.66.1,<5.0.0)
